pydantic_api/base/__init__.py
pydantic_api/base/base_model.py
pydantic_api_models-0.0.2.dist-info/LICENSE
pydantic_api_models-0.0.2.dist-info/METADATA
pydantic_api_models-0.0.2.dist-info/WHEEL
pydantic_api_models-0.0.2.dist-info/RECORD
